flaretool/VERSION.py
flaretool/__init__.py
flaretool/basemodels.py
flaretool/command.py
flaretool/common.py
flaretool/common.pyi
flaretool/constants.py
flaretool/decorators.py
flaretool/enums.py
flaretool/errors.py
flaretool/logger.py
flaretool/settings.py
flaretool/utills.py
flaretool/ddns/DdnsService.py
flaretool/ddns/__init__.py
flaretool/ddns/errors.py
flaretool/ddns/models.py
flaretool/funcs/__init__.py
flaretool/funcs/amazon.py
flaretool/funcs/models.py
flaretool/funcs/tracking.py
flaretool/holiday/JapaneseHolidays.py
flaretool/holiday/JapaneseHolidaysOnline.py
flaretool/holiday/__init__.py
flaretool/holiday/errors.py
flaretool/holiday/models.py
flaretool/nettool/__init__.py
flaretool/nettool/common.py
flaretool/nettool/models.py
flaretool/shorturl/ShortUrlService.py
flaretool/shorturl/__init__.py
flaretool/shorturl/errors.py
flaretool/shorturl/models.py
flaretool-0.2.8.dist-info/licenses/LICENSE
flaretool-0.2.8.dist-info/METADATA
flaretool-0.2.8.dist-info/WHEEL
flaretool-0.2.8.dist-info/entry_points.txt
flaretool-0.2.8.dist-info/top_level.txt
flaretool-0.2.8.dist-info/RECORD
