Metadata-Version: 2.4
Name: flaretool
Version: 0.2.8
Summary: this is flarebrow package
Home-page: https://main.flarebrow.com
Author: flarebrow
License: MIT
Project-URL: Documentation, https://flarebrow.github.io/flaretool/
Project-URL: Source, https://github.com/flarebrow/flaretool
Project-URL: Funding, https://github.com/sponsors/flarebrow
Keywords: flaretool
Classifier: Programming Language :: Python :: 3.9
Classifier: Programming Language :: Python :: 3.10
Classifier: Programming Language :: Python :: 3.11
Classifier: Programming Language :: Python :: 3.12
Classifier: License :: OSI Approved :: MIT License
Classifier: Operating System :: OS Independent
Requires-Python: >=3.9
License-File: LICENSE
Requires-Dist: annotated-types>=0.7.0
Requires-Dist: beautifulsoup4>=4.12.3
Requires-Dist: certifi>=2024.6.2
Requires-Dist: charset-normalizer>=3.3.2
Requires-Dist: future>=1.0.0
Requires-Dist: idna>=3.7
Requires-Dist: packaging>=24.0
Requires-Dist: pycodestyle>=2.11.1
Requires-Dist: pydantic>=2.7.3
Requires-Dist: pydantic-settings>=2.3.1
Requires-Dist: pydantic_core>=2.18.4
Requires-Dist: python-dateutil>=2.9.0.post0
Requires-Dist: python-dotenv>=1.0.1
Requires-Dist: python-whois>=0.9.4
Requires-Dist: requests>=2.32.3
Requires-Dist: six>=1.16.0
Requires-Dist: soupsieve>=2.5
Requires-Dist: tomli>=2.0.1
Requires-Dist: typing_extensions>=4.12.1
Requires-Dist: urllib3>=2.2.1
Dynamic: author
Dynamic: classifier
Dynamic: description
Dynamic: description-content-type
Dynamic: home-page
Dynamic: keywords
Dynamic: license
Dynamic: license-file
Dynamic: project-url
Dynamic: requires-dist
Dynamic: requires-python
Dynamic: summary
